[
    {
        "user": "AldricB",
        "conceptSlug": "art-cinetique",
        "images": []
    },
    {
        "user": "AldricB",
        "conceptSlug": "formes-architecturales",
        "images": []
    },
    {
        "user": "AldricB",
        "conceptSlug": "paysages-grandioses",
        "images": []
    },
    {
        "user": "AldricB",
        "conceptSlug": "portraits-d-athletes",
        "images": []
    },
    {
        "user": "AndyB",
        "conceptSlug": "astrophotographie",
        "images": []
    },
    {
        "user": "AndyB",
        "conceptSlug": "images-360",
        "images": []
    },
    {
        "user": "AndyB",
        "conceptSlug": "juxtapositions",
        "images": []
    },
    {
        "user": "AndyB",
        "conceptSlug": "reflexions-sur-l-objet",
        "images": []
    },
    {
        "user": "AnthonnyL",
        "conceptSlug": "ambiguites-visuelles",
        "images": []
    },
    {
        "user": "AnthonnyL",
        "conceptSlug": "explorations-souterraines",
        "images": []
    },
    {
        "user": "AnthonnyL",
        "conceptSlug": "gastronomie-mondiale",
        "images": []
    },
    {
        "user": "AnthonnyL",
        "conceptSlug": "storyboards-de-films",
        "images": []
    },
    {
        "user": "CamilleC",
        "conceptSlug": "bokeh-creatif",
        "images": []
    },
    {
        "user": "CamilleC",
        "conceptSlug": "faune-rare",
        "images": []
    },
    {
        "user": "CamilleC",
        "conceptSlug": "iconographie-religieuse",
        "images": []
    },
    {
        "user": "CamilleC",
        "conceptSlug": "photographie-minimaliste",
        "images": []
    },
    {
        "user": "ClementB",
        "conceptSlug": "bande-dessinee",
        "images": []
    },
    {
        "user": "ClementB",
        "conceptSlug": "changement-climatique",
        "images": []
    },
    {
        "user": "ClementB",
        "conceptSlug": "illustrations-folkloriques",
        "images": []
    },
    {
        "user": "ClementB",
        "conceptSlug": "longue-exposition",
        "images": []
    },
    {
        "user": "DominicR",
        "conceptSlug": "images-ui-ux",
        "images": []
    },
    {
        "user": "DominicR",
        "conceptSlug": "mouvements-en-plein-action",
        "images": []
    },
    {
        "user": "DominicR",
        "conceptSlug": "photo-animaliere",
        "images": []
    },
    {
        "user": "DominicR",
        "conceptSlug": "visualisation-vr-ar",
        "images": []
    },
    {
        "user": "EmilieF",
        "conceptSlug": "cartographie",
        "images": []
    },
    {
        "user": "EmilieF",
        "conceptSlug": "cyberspace",
        "images": []
    },
    {
        "user": "EmilieF",
        "conceptSlug": "diagrammes-scientifiques",
        "images": []
    },
    {
        "user": "EmilieF",
        "conceptSlug": "photos-en-sepia",
        "images": []
    },
    {
        "user": "EmilieF",
        "conceptSlug": "tutoriels-visuels",
        "images": []
    },
    {
        "user": "EmmanuelT",
        "conceptSlug": "ambiance-et-atmosphere",
        "images": []
    },
    {
        "user": "EmmanuelT",
        "conceptSlug": "infographies",
        "images": []
    },
    {
        "user": "EmmanuelT",
        "conceptSlug": "mises-en-scene-surrealistes",
        "images": []
    },
    {
        "user": "EmmanuelT",
        "conceptSlug": "storyboard",
        "images": []
    },
    {
        "user": "FelixM",
        "conceptSlug": "chat-occulte-cinema",
        "images": [
            {
                "path": "FelixM/chat-occulte-cinema/1.ai.png",
                "width": 1024,
                "height": 1024,
                "ratio": 1
            },
            {
                "path": "FelixM/chat-occulte-cinema/2.ai.png",
                "width": 1024,
                "height": 1024,
                "ratio": 1
            },
            {
                "path": "FelixM/chat-occulte-cinema/3.ai.png",
                "width": 1024,
                "height": 1024,
                "ratio": 1
            },
            {
                "path": "FelixM/chat-occulte-cinema/4.ai.png",
                "width": 1024,
                "height": 1024,
                "ratio": 1
            }
        ]
    },
    {
        "user": "FelixM",
        "conceptSlug": "crapstraction",
        "images": [
            {
                "path": "FelixM/crapstraction/1.webp",
                "width": 700,
                "height": 466,
                "ratio": 1.502145922746781
            },
            {
                "path": "FelixM/crapstraction/2.webp",
                "width": 700,
                "height": 466,
                "ratio": 1.502145922746781
            },
            {
                "path": "FelixM/crapstraction/3.webp",
                "width": 700,
                "height": 466,
                "ratio": 1.502145922746781
            },
            {
                "path": "FelixM/crapstraction/4.webp",
                "width": 700,
                "height": 466,
                "ratio": 1.502145922746781
            },
            {
                "path": "FelixM/crapstraction/5.webp",
                "width": 700,
                "height": 466,
                "ratio": 1.502145922746781
            },
            {
                "path": "FelixM/crapstraction/6.webp",
                "width": 700,
                "height": 466,
                "ratio": 1.502145922746781
            }
        ]
    },
    {
        "user": "FelixM",
        "conceptSlug": "cremelted",
        "images": [
            {
                "path": "FelixM/cremelted/1.ai.png",
                "width": 1024,
                "height": 1024,
                "ratio": 1
            },
            {
                "path": "FelixM/cremelted/2.ai.png",
                "width": 1024,
                "height": 1024,
                "ratio": 1
            },
            {
                "path": "FelixM/cremelted/3.ai.png",
                "width": 1024,
                "height": 1024,
                "ratio": 1
            },
            {
                "path": "FelixM/cremelted/4.ai.png",
                "width": 1024,
                "height": 1024,
                "ratio": 1
            }
        ]
    },
    {
        "user": "FelixM",
        "conceptSlug": "mon-auto-ma-famille-stereotype-annees-70",
        "images": [
            {
                "path": "FelixM/mon-auto-ma-famille-stereotype-annees-70/1.ai.png",
                "width": 1024,
                "height": 1024,
                "ratio": 1
            },
            {
                "path": "FelixM/mon-auto-ma-famille-stereotype-annees-70/2.ai.png",
                "width": 1024,
                "height": 1024,
                "ratio": 1
            },
            {
                "path": "FelixM/mon-auto-ma-famille-stereotype-annees-70/3.ai.png",
                "width": 1024,
                "height": 1024,
                "ratio": 1
            }
        ]
    },
    {
        "user": "FelixM",
        "conceptSlug": "photo-de-famille-maladroite-90",
        "images": [
            {
                "path": "FelixM/photo-de-famille-maladroite-90/1.ai.png",
                "width": 1024,
                "height": 1024,
                "ratio": 1
            },
            {
                "path": "FelixM/photo-de-famille-maladroite-90/10.ai.png",
                "width": 1024,
                "height": 1024,
                "ratio": 1
            },
            {
                "path": "FelixM/photo-de-famille-maladroite-90/2.ai.png",
                "width": 1024,
                "height": 1024,
                "ratio": 1
            },
            {
                "path": "FelixM/photo-de-famille-maladroite-90/3.ai.png",
                "width": 1024,
                "height": 1024,
                "ratio": 1
            },
            {
                "path": "FelixM/photo-de-famille-maladroite-90/4.ai.png",
                "width": 1024,
                "height": 1024,
                "ratio": 1
            },
            {
                "path": "FelixM/photo-de-famille-maladroite-90/5.ai.png",
                "width": 1024,
                "height": 1024,
                "ratio": 1
            },
            {
                "path": "FelixM/photo-de-famille-maladroite-90/6.ai.png",
                "width": 1024,
                "height": 1024,
                "ratio": 1
            },
            {
                "path": "FelixM/photo-de-famille-maladroite-90/7.ai.png",
                "width": 1024,
                "height": 1024,
                "ratio": 1
            },
            {
                "path": "FelixM/photo-de-famille-maladroite-90/8.ai.png",
                "width": 1024,
                "height": 1024,
                "ratio": 1
            },
            {
                "path": "FelixM/photo-de-famille-maladroite-90/9.ai.png",
                "width": 1024,
                "height": 1024,
                "ratio": 1
            }
        ]
    },
    {
        "user": "FlorenceL",
        "conceptSlug": "artefacts-visuels-accidentels",
        "images": [
            {
                "path": "FlorenceL/artefacts-visuels-accidentels/1460504852-image.jpg",
                "width": 3264,
                "height": 2448,
                "ratio": 1.3333333333333333
            },
            {
                "path": "FlorenceL/artefacts-visuels-accidentels/1OIG.ia.ori.jpg",
                "width": 1024,
                "height": 1024,
                "ratio": 1
            },
            {
                "path": "FlorenceL/artefacts-visuels-accidentels/2023-09-12 142139.png",
                "width": 461,
                "height": 470,
                "ratio": 0.9808510638297873
            },
            {
                "path": "FlorenceL/artefacts-visuels-accidentels/2023-09-12 142301.png",
                "width": 668,
                "height": 456,
                "ratio": 1.4649122807017543
            },
            {
                "path": "FlorenceL/artefacts-visuels-accidentels/bug.jpg",
                "width": 824,
                "height": 509,
                "ratio": 1.618860510805501
            },
            {
                "path": "FlorenceL/artefacts-visuels-accidentels/drrr.jpg",
                "width": 426,
                "height": 569,
                "ratio": 0.7486818980667839
            },
            {
                "path": "FlorenceL/artefacts-visuels-accidentels/glitch-03-1024x576.png",
                "width": 1024,
                "height": 576,
                "ratio": 1.7777777777777777
            },
            {
                "path": "FlorenceL/artefacts-visuels-accidentels/image_94993.jpg",
                "width": 600,
                "height": 368,
                "ratio": 1.6304347826086956
            },
            {
                "path": "FlorenceL/artefacts-visuels-accidentels/soleilbloom2.jpg",
                "width": 500,
                "height": 333,
                "ratio": 1.5015015015015014
            },
            {
                "path": "FlorenceL/artefacts-visuels-accidentels/téléchargement.jpg",
                "width": 227,
                "height": 222,
                "ratio": 1.0225225225225225
            }
        ]
    },
    {
        "user": "FlorenceL",
        "conceptSlug": "collages-surrealistes",
        "images": [
            {
                "path": "FlorenceL/collages-surrealistes/2b73e5465870dbf3213cb4735ddd0317.png",
                "width": 1000,
                "height": 1000,
                "ratio": 1
            },
            {
                "path": "FlorenceL/collages-surrealistes/Mohanad-Shuraideh-collage-espace.jpg",
                "width": 1400,
                "height": 1400,
                "ratio": 1
            },
            {
                "path": "FlorenceL/collages-surrealistes/Sandra-Reis-collage-fisheye-5-580x812.jpg",
                "width": 580,
                "height": 812,
                "ratio": 0.7142857142857143
            },
            {
                "path": "FlorenceL/collages-surrealistes/artedelph-refletsurrealiste-peinturecollage-portraitpop_artstr-theartcycle-photo_principale.jpg",
                "width": 648,
                "height": 681,
                "ratio": 0.9515418502202643
            },
            {
                "path": "FlorenceL/collages-surrealistes/collages-Mohanad-Shuraideh.jpg",
                "width": 1400,
                "height": 1400,
                "ratio": 1
            },
            {
                "path": "FlorenceL/collages-surrealistes/des-collages-surrealistes-pour-accepter-son-corps.jpg",
                "width": 1200,
                "height": 755,
                "ratio": 1.5894039735099337
            },
            {
                "path": "FlorenceL/collages-surrealistes/femme.jpg",
                "width": 768,
                "height": 1077,
                "ratio": 0.713091922005571
            },
            {
                "path": "FlorenceL/collages-surrealistes/images.jpg",
                "width": 194,
                "height": 260,
                "ratio": 0.7461538461538462
            },
            {
                "path": "FlorenceL/collages-surrealistes/map-collage.jpg",
                "width": 600,
                "height": 650,
                "ratio": 0.9230769230769231
            },
            {
                "path": "FlorenceL/collages-surrealistes/poisson_homme.jpg",
                "width": 699,
                "height": 989,
                "ratio": 0.7067745197168858
            }
        ]
    },
    {
        "user": "FlorenceL",
        "conceptSlug": "patterns-repetitions",
        "images": []
    },
    {
        "user": "FlorenceL",
        "conceptSlug": "reportage-de-guerre",
        "images": [
            {
                "path": "FlorenceL/reportage-de-guerre/000_32JD9DD.jpg",
                "width": 1584,
                "height": 891,
                "ratio": 1.7777777777777777
            },
            {
                "path": "FlorenceL/reportage-de-guerre/2023-09-12 130037.png",
                "width": 856,
                "height": 496,
                "ratio": 1.7258064516129032
            },
            {
                "path": "FlorenceL/reportage-de-guerre/civil_fuyant.jpg",
                "width": 612,
                "height": 408,
                "ratio": 1.5
            },
            {
                "path": "FlorenceL/reportage-de-guerre/gettyimages-1238745447-612x612.jpg",
                "width": 612,
                "height": 408,
                "ratio": 1.5
            },
            {
                "path": "FlorenceL/reportage-de-guerre/gettyimages-464495524-612x612.jpg",
                "width": 612,
                "height": 408,
                "ratio": 1.5
            },
            {
                "path": "FlorenceL/reportage-de-guerre/guerre.png",
                "width": 1122,
                "height": 742,
                "ratio": 1.5121293800539084
            },
            {
                "path": "FlorenceL/reportage-de-guerre/istockphoto-1387105111-612x612.jpg",
                "width": 612,
                "height": 408,
                "ratio": 1.5
            },
            {
                "path": "FlorenceL/reportage-de-guerre/istockphoto-941116916-612x612.jpg",
                "width": 612,
                "height": 405,
                "ratio": 1.511111111111111
            },
            {
                "path": "FlorenceL/reportage-de-guerre/soldat_guerre.png",
                "width": 1050,
                "height": 693,
                "ratio": 1.5151515151515151
            },
            {
                "path": "FlorenceL/reportage-de-guerre/ukraine.png",
                "width": 857,
                "height": 496,
                "ratio": 1.7278225806451613
            }
        ]
    },
    {
        "user": "JeanChristopheZ",
        "conceptSlug": "portraits-culturels",
        "images": [
            {
                "path": "JeanChristopheZ/portraits-culturels/IMG_20230911_121544.jpg",
                "width": 1079,
                "height": 1340,
                "ratio": 0.8052238805970149
            },
            {
                "path": "JeanChristopheZ/portraits-culturels/IMG_20230911_121558.jpg",
                "width": 1080,
                "height": 1334,
                "ratio": 0.8095952023988006
            },
            {
                "path": "JeanChristopheZ/portraits-culturels/IMG_20230911_121609.jpg",
                "width": 1080,
                "height": 1363,
                "ratio": 0.7923697725605282
            },
            {
                "path": "JeanChristopheZ/portraits-culturels/IMG_20230911_121637.jpg",
                "width": 1080,
                "height": 1354,
                "ratio": 0.7976366322008862
            },
            {
                "path": "JeanChristopheZ/portraits-culturels/IMG_20230911_121650.jpg",
                "width": 1080,
                "height": 744,
                "ratio": 1.4516129032258065
            },
            {
                "path": "JeanChristopheZ/portraits-culturels/IMG_20230911_121734.jpg",
                "width": 1077,
                "height": 1198,
                "ratio": 0.8989983305509182
            },
            {
                "path": "JeanChristopheZ/portraits-culturels/IMG_20230911_121744.jpg",
                "width": 1080,
                "height": 1361,
                "ratio": 0.7935341660543718
            },
            {
                "path": "JeanChristopheZ/portraits-culturels/IMG_20230911_121754.jpg",
                "width": 1080,
                "height": 810,
                "ratio": 1.3333333333333333
            },
            {
                "path": "JeanChristopheZ/portraits-culturels/IMG_20230911_121832.jpg",
                "width": 1080,
                "height": 1117,
                "ratio": 0.9668755595344674
            },
            {
                "path": "JeanChristopheZ/portraits-culturels/IMG_20230911_121840.jpg",
                "width": 1080,
                "height": 1049,
                "ratio": 1.0295519542421354
            }
        ]
    },
    {
        "user": "JeanChristopheZ",
        "conceptSlug": "socio-numerique",
        "images": [
            {
                "path": "JeanChristopheZ/socio-numerique/317bcc47700414522d1b1260a0232819.jpg",
                "width": 564,
                "height": 382,
                "ratio": 1.4764397905759161
            },
            {
                "path": "JeanChristopheZ/socio-numerique/44cf2b963826d06e5cc11f149e685ac9.jpg",
                "width": 564,
                "height": 423,
                "ratio": 1.3333333333333333
            },
            {
                "path": "JeanChristopheZ/socio-numerique/6a46bc18ddb5e6ce36d8dfe12d50f067.jpg",
                "width": 331,
                "height": 500,
                "ratio": 0.662
            },
            {
                "path": "JeanChristopheZ/socio-numerique/6db41a187398ceaf30cd669d43473a21.jpg",
                "width": 564,
                "height": 376,
                "ratio": 1.5
            },
            {
                "path": "JeanChristopheZ/socio-numerique/7929990411635186d5369a9967bca53a.jpg",
                "width": 564,
                "height": 317,
                "ratio": 1.779179810725552
            },
            {
                "path": "JeanChristopheZ/socio-numerique/84d741c9262a5dde52e17b474dd4bb12.jpg",
                "width": 400,
                "height": 300,
                "ratio": 1.3333333333333333
            },
            {
                "path": "JeanChristopheZ/socio-numerique/c977a557dc03b18566c7a65deec7c044.jpg",
                "width": 564,
                "height": 840,
                "ratio": 0.6714285714285714
            },
            {
                "path": "JeanChristopheZ/socio-numerique/de56be8db1769ef63590c87d0528db6c.jpg",
                "width": 564,
                "height": 376,
                "ratio": 1.5
            },
            {
                "path": "JeanChristopheZ/socio-numerique/eeb991fbc257198605362706f3372c84.jpg",
                "width": 564,
                "height": 322,
                "ratio": 1.7515527950310559
            },
            {
                "path": "JeanChristopheZ/socio-numerique/kid_ipad.png",
                "width": 564,
                "height": 846,
                "ratio": 0.6666666666666666
            }
        ]
    },
    {
        "user": "JeanChristopheZ",
        "conceptSlug": "souvenirs",
        "images": [
            {
                "path": "JeanChristopheZ/souvenirs/04ffe4f5af8907341e51c9ca39676bf5.jpg",
                "width": 563,
                "height": 495,
                "ratio": 1.1373737373737374
            },
            {
                "path": "JeanChristopheZ/souvenirs/0c6371ed06ab4fd4b76e07f4f39bcf55.jpg",
                "width": 432,
                "height": 640,
                "ratio": 0.675
            },
            {
                "path": "JeanChristopheZ/souvenirs/4d07e7feb89a371527d423fa6425c500.jpg",
                "width": 564,
                "height": 840,
                "ratio": 0.6714285714285714
            },
            {
                "path": "JeanChristopheZ/souvenirs/4f22292b37b9d9569e520339dbba04ae.jpg",
                "width": 564,
                "height": 752,
                "ratio": 0.75
            },
            {
                "path": "JeanChristopheZ/souvenirs/5b5362efeba8a4cc69353c5e0f90c5dc.jpg",
                "width": 500,
                "height": 667,
                "ratio": 0.7496251874062968
            },
            {
                "path": "JeanChristopheZ/souvenirs/c40356601b86da4cdd4a66874e7a9161.jpg",
                "width": 564,
                "height": 846,
                "ratio": 0.6666666666666666
            },
            {
                "path": "JeanChristopheZ/souvenirs/ded4c71a0f88d5d2a26807fdf14c550a.jpg",
                "width": 300,
                "height": 250,
                "ratio": 1.2
            },
            {
                "path": "JeanChristopheZ/souvenirs/e22e092ac10bac64981f54c8fdb7e956.jpg",
                "width": 358,
                "height": 531,
                "ratio": 0.6741996233521658
            },
            {
                "path": "JeanChristopheZ/souvenirs/e47375edb76bc853997cc1dbb971aaef.jpg",
                "width": 400,
                "height": 400,
                "ratio": 1
            },
            {
                "path": "JeanChristopheZ/souvenirs/f2f1cfca494e68b180260f7bf74a94f6.jpg",
                "width": 570,
                "height": 858,
                "ratio": 0.6643356643356644
            }
        ]
    },
    {
        "user": "JeanChristopheZ",
        "conceptSlug": "villes-la-nuit",
        "images": [
            {
                "path": "JeanChristopheZ/villes-la-nuit/IMG_0636.JPG",
                "width": 5184,
                "height": 3456,
                "ratio": 1.5
            },
            {
                "path": "JeanChristopheZ/villes-la-nuit/IMG_0642.JPG",
                "width": 5184,
                "height": 3456,
                "ratio": 1.5
            },
            {
                "path": "JeanChristopheZ/villes-la-nuit/IMG_0644.JPG",
                "width": 5184,
                "height": 3456,
                "ratio": 1.5
            },
            {
                "path": "JeanChristopheZ/villes-la-nuit/IMG_0662.JPG",
                "width": 5184,
                "height": 3456,
                "ratio": 1.5
            },
            {
                "path": "JeanChristopheZ/villes-la-nuit/IMG_0668.jpg",
                "width": 3041,
                "height": 4562,
                "ratio": 0.6665935992985532
            },
            {
                "path": "JeanChristopheZ/villes-la-nuit/IMG_0684.JPG",
                "width": 5184,
                "height": 3456,
                "ratio": 1.5
            },
            {
                "path": "JeanChristopheZ/villes-la-nuit/IMG_0701.JPG",
                "width": 5184,
                "height": 3456,
                "ratio": 1.5
            },
            {
                "path": "JeanChristopheZ/villes-la-nuit/IMG_0758.JPG",
                "width": 5184,
                "height": 3456,
                "ratio": 1.5
            },
            {
                "path": "JeanChristopheZ/villes-la-nuit/IMG_0764.JPG",
                "width": 5184,
                "height": 3456,
                "ratio": 1.5
            },
            {
                "path": "JeanChristopheZ/villes-la-nuit/IMG_0767.JPG",
                "width": 5184,
                "height": 3456,
                "ratio": 1.5
            }
        ]
    },
    {
        "user": "JustinL",
        "conceptSlug": "dualite",
        "images": []
    },
    {
        "user": "JustinL",
        "conceptSlug": "lifestyle-urbain",
        "images": []
    },
    {
        "user": "JustinL",
        "conceptSlug": "visualisation-de-donnees",
        "images": []
    },
    {
        "user": "JustinL",
        "conceptSlug": "visuels-holographiques",
        "images": []
    },
    {
        "user": "LauraGB",
        "conceptSlug": "cartographie-historique",
        "images": [
            {
                "path": "LauraGB/cartographie-historique/5b722188135c8d702b274fd8ffead86e--old-maps-antique-maps.jpeg",
                "width": 736,
                "height": 627,
                "ratio": 1.1738437001594897
            },
            {
                "path": "LauraGB/cartographie-historique/71430.jpeg",
                "width": 1600,
                "height": 1327,
                "ratio": 1.2057272042200453
            },
            {
                "path": "LauraGB/cartographie-historique/AdobeStock_18717115.jpeg",
                "width": 3120,
                "height": 2080,
                "ratio": 1.5
            },
            {
                "path": "LauraGB/cartographie-historique/AdobeStock_190809510.jpeg",
                "width": 6016,
                "height": 3982,
                "ratio": 1.5107985936715218
            },
            {
                "path": "LauraGB/cartographie-historique/AdobeStock_190810514.jpeg",
                "width": 5489,
                "height": 3149,
                "ratio": 1.7430930454112417
            },
            {
                "path": "LauraGB/cartographie-historique/AdobeStock_227536539.jpeg",
                "width": 4779,
                "height": 6069,
                "ratio": 0.7874443895205141
            },
            {
                "path": "LauraGB/cartographie-historique/Political_Divisions_of_the_Indian_Empire,_1909.jpeg",
                "width": 734,
                "height": 599,
                "ratio": 1.2253756260434057
            },
            {
                "path": "LauraGB/cartographie-historique/antique-map-of-the-persian-empire-mountain-dreams.jpeg",
                "width": 900,
                "height": 710,
                "ratio": 1.267605633802817
            },
            {
                "path": "LauraGB/cartographie-historique/m09295.webp",
                "width": 1000,
                "height": 724,
                "ratio": 1.3812154696132597
            },
            {
                "path": "LauraGB/cartographie-historique/wmark-persia_india.webp",
                "width": 1500,
                "height": 1272,
                "ratio": 1.179245283018868
            }
        ]
    },
    {
        "user": "LauraGB",
        "conceptSlug": "icones-historiques",
        "images": []
    },
    {
        "user": "LauraGB",
        "conceptSlug": "infographies",
        "images": [
            {
                "path": "LauraGB/infographies/AdobeStock_120108826.jpeg",
                "width": 3873,
                "height": 3873,
                "ratio": 1
            },
            {
                "path": "LauraGB/infographies/AdobeStock_192351281.jpeg",
                "width": 4330,
                "height": 3464,
                "ratio": 1.25
            },
            {
                "path": "LauraGB/infographies/AdobeStock_512114101.jpeg",
                "width": 6614,
                "height": 4724,
                "ratio": 1.4000846740050805
            },
            {
                "path": "LauraGB/infographies/AdobeStock_512603110.jpeg",
                "width": 5965,
                "height": 5965,
                "ratio": 1
            },
            {
                "path": "LauraGB/infographies/Elements-of-Design2.jpeg",
                "width": 992,
                "height": 620,
                "ratio": 1.6
            },
            {
                "path": "LauraGB/infographies/capture-decran-2019-07-03-a-10-52-29.png",
                "width": 312,
                "height": 680,
                "ratio": 0.4588235294117647
            },
            {
                "path": "LauraGB/infographies/gravites_2015-2019_chiens.png",
                "width": 4740,
                "height": 2383,
                "ratio": 1.9890893831305079
            },
            {
                "path": "LauraGB/infographies/infographie-nomination-7-3.jpeg",
                "width": 610,
                "height": 431,
                "ratio": 1.4153132250580047
            },
            {
                "path": "LauraGB/infographies/inspiration-infographie-1.webp",
                "width": 700,
                "height": 491,
                "ratio": 1.4256619144602851
            },
            {
                "path": "LauraGB/infographies/julienrio.com-infographic-2.png",
                "width": 660,
                "height": 427,
                "ratio": 1.5456674473067915
            }
        ]
    },
    {
        "user": "LauraGB",
        "conceptSlug": "paysages-dystopiques",
        "images": [
            {
                "path": "LauraGB/paysages-dystopiques/eyJidWNrZXQiOiJzaW5ndWxhcnQtd2Vic2l0ZS1wcm9kIiwia2V5IjoiYXJ0d29ya3NcL3YyXC9jcm9wcGVkXC81NjY5XC9tYWluXC96b29tXC8xNjgxODkwX2QzZTc0MzAyNmY3ZDI0ZGM0ODk2NTEwMzczMWRlZTMzLmpwZWciLCJlZGl0cyI6eyJyZXNpemUiOnsid2lkdGgiOjMwMCwiZml0IjoiaW5zaWRlIn0sInR.webp",
                "width": 300,
                "height": 408,
                "ratio": 0.7352941176470589
            },
            {
                "path": "LauraGB/paysages-dystopiques/eyJidWNrZXQiOiJzaW5ndWxhcnQtd2Vic2l0ZS1wcm9kIiwia2V5IjoiYXJ0d29ya3NcL3YyXC9jcm9wcGVkXC83NDExXC9tYWluXC96b29tXC8xNDU0MzYzXzQ1ZDI0NDcyNTIzNThkNjQ5NmQzOTRmNTc4YjNmNDY4LmpwZWciLCJlZGl0cyI6eyJyZXNpemUiOnsid2lkdGgiOjMwMCwiZml0IjoiaW5zaWRlIn0sInR.webp",
                "width": 300,
                "height": 240,
                "ratio": 1.25
            },
            {
                "path": "LauraGB/paysages-dystopiques/eyJidWNrZXQiOiJzaW5ndWxhcnQtd2Vic2l0ZS1wcm9kIiwia2V5IjoiYXJ0d29ya3NcL3YyXC9jcm9wcGVkXC8xMjAzN1wvbWFpblwvem9vbVwvMTY5MjQ1MF82ZGE0NTI3NTE2MjAwZmFmYmMxMDRkMmEzMmVmMDg5MS5qcGVnIiwiZWRpdHMiOnsicmVzaXplIjp7IndpZHRoIjozMDAsImZpdCI6Imluc2lkZSJ9LCJ.webp",
                "width": 300,
                "height": 212,
                "ratio": 1.4150943396226414
            },
            {
                "path": "LauraGB/paysages-dystopiques/eyJidWNrZXQiOiJzaW5ndWxhcnQtd2Vic2l0ZS1wcm9kIiwia2V5IjoiYXJ0d29ya3NcL3YyXC9jcm9wcGVkXC8xNjE2XC9tYWluXC96b29tXC8xNjg4NTQ2XzFhZTAyMGEwYWRhYjIxYmYzMTY0NjQ2NmM5MmJlN2EyLmpwZWciLCJlZGl0cyI6eyJyZXNpemUiOnsid2lkdGgiOjMwMCwiZml0IjoiaW5zaWRlIn0sInR.webp",
                "width": 300,
                "height": 298,
                "ratio": 1.0067114093959733
            },
            {
                "path": "LauraGB/paysages-dystopiques/eyJidWNrZXQiOiJzaW5ndWxhcnQtd2Vic2l0ZS1wcm9kIiwia2V5IjoiYXJ0d29ya3NcL3YyXC9jcm9wcGVkXC8xODAyM1wvbWFpblwvem9vbVwvMTY4ODgwMV8zMWRjYmNjNjk2ZWZkN2EwNzM3ZGYyMjM5Mjk5NGE5NS5qcGVnIiwiZWRpdHMiOnsicmVzaXplIjp7IndpZHRoIjozMDAsImZpdCI6Imluc2lkZSJ9LCJ.webp",
                "width": 300,
                "height": 187,
                "ratio": 1.6042780748663101
            },
            {
                "path": "LauraGB/paysages-dystopiques/eyJidWNrZXQiOiJzaW5ndWxhcnQtd2Vic2l0ZS1wcm9kIiwia2V5IjoiYXJ0d29ya3NcL3YyXC9jcm9wcGVkXC8yNzYzM1wvbWFpblwvem9vbVwvMTY4MTY3N19mOTBjZDEzNzU0ZTk3YjhjMTdiMTMzMGVlOGQyZTIzYi5qcGVnIiwiZWRpdHMiOnsicmVzaXplIjp7IndpZHRoIjozMDAsImZpdCI6Imluc2lkZSJ9LCJ.webp",
                "width": 300,
                "height": 227,
                "ratio": 1.3215859030837005
            },
            {
                "path": "LauraGB/paysages-dystopiques/eyJidWNrZXQiOiJzaW5ndWxhcnQtd2Vic2l0ZS1wcm9kIiwia2V5IjoiYXJ0d29ya3NcL3YyXC9jcm9wcGVkXC8yOTIwM1wvbWFpblwvem9vbVwvMTU5Mjg4MF8zZmY3NzVmNzY5Njc2NzY4NmQ0YTZiODM0YzlkZjBjZi5qcGVnIiwiZWRpdHMiOnsicmVzaXplIjp7IndpZHRoIjozMDAsImZpdCI6Imluc2lkZSJ9LCJ.webp",
                "width": 300,
                "height": 301,
                "ratio": 0.9966777408637874
            },
            {
                "path": "LauraGB/paysages-dystopiques/eyJidWNrZXQiOiJzaW5ndWxhcnQtd2Vic2l0ZS1wcm9kIiwia2V5IjoiYXJ0d29ya3NcL3YyXC9jcm9wcGVkXC8zNDcyOVwvbWFpblwvem9vbVwvMTY4MjYwN19mNmUwMzRhMTQ0OWY5NzFlM2M5ODc1MjRkYjQ3MmFkMy5qcGVnIiwiZWRpdHMiOnsicmVzaXplIjp7IndpZHRoIjozMDAsImZpdCI6Imluc2lkZSJ9LCJ.webp",
                "width": 300,
                "height": 455,
                "ratio": 0.6593406593406593
            },
            {
                "path": "LauraGB/paysages-dystopiques/lot.jpeg",
                "width": 720,
                "height": 469,
                "ratio": 1.535181236673774
            },
            {
                "path": "LauraGB/paysages-dystopiques/paysage apocalyptique.jpg",
                "width": 768,
                "height": 1152,
                "ratio": 0.6666666666666666
            }
        ]
    },
    {
        "user": "LaurenceD",
        "conceptSlug": "epoques-revolues",
        "images": []
    },
    {
        "user": "LaurenceD",
        "conceptSlug": "haute-couture",
        "images": []
    },
    {
        "user": "LaurenceD",
        "conceptSlug": "paysages-urbains-nocturnes",
        "images": []
    },
    {
        "user": "LaurenceD",
        "conceptSlug": "photos-macro",
        "images": []
    },
    {
        "user": "MariaB",
        "conceptSlug": "art-algorithmique",
        "images": []
    },
    {
        "user": "MariaB",
        "conceptSlug": "ecotech",
        "images": []
    },
    {
        "user": "MariaB",
        "conceptSlug": "images-futuristes",
        "images": []
    },
    {
        "user": "MariaB",
        "conceptSlug": "tutoriels-visuels",
        "images": []
    },
    {
        "user": "MaudeL",
        "conceptSlug": "affiches-de-protestation",
        "images": []
    },
    {
        "user": "MaudeL",
        "conceptSlug": "foules-et-interactions",
        "images": []
    },
    {
        "user": "MaudeL",
        "conceptSlug": "metamorphose",
        "images": []
    },
    {
        "user": "MaudeL",
        "conceptSlug": "phenomenes-naturels",
        "images": []
    },
    {
        "user": "MaximC",
        "conceptSlug": "anthropocene",
        "images": []
    },
    {
        "user": "MaximC",
        "conceptSlug": "danse-en-mouvement",
        "images": []
    },
    {
        "user": "MaximC",
        "conceptSlug": "identites-hybrides",
        "images": []
    },
    {
        "user": "MaximC",
        "conceptSlug": "techno-utopie",
        "images": []
    },
    {
        "user": "MedericP",
        "conceptSlug": "brutalisme",
        "images": []
    },
    {
        "user": "MedericP",
        "conceptSlug": "montages-surrealistes",
        "images": []
    },
    {
        "user": "MedericP",
        "conceptSlug": "mouvements-sociaux",
        "images": []
    },
    {
        "user": "MedericP",
        "conceptSlug": "ruines-et-reliques",
        "images": []
    },
    {
        "user": "MeryemB",
        "conceptSlug": "art-de-rue-graffiti",
        "images": []
    },
    {
        "user": "MeryemB",
        "conceptSlug": "moments-decisifs",
        "images": []
    },
    {
        "user": "MeryemB",
        "conceptSlug": "objets-en-mouvement",
        "images": []
    },
    {
        "user": "MeryemB",
        "conceptSlug": "visualisation-musicale",
        "images": []
    },
    {
        "user": "NoemiL",
        "conceptSlug": "contrastes-culturels",
        "images": []
    },
    {
        "user": "NoemiL",
        "conceptSlug": "formes-et-motifs",
        "images": []
    },
    {
        "user": "NoemiL",
        "conceptSlug": "innovations-technologiques",
        "images": []
    },
    {
        "user": "NoemiL",
        "conceptSlug": "photosjournalisme",
        "images": []
    },
    {
        "user": "NoemieP",
        "conceptSlug": "art-de-rue",
        "images": []
    },
    {
        "user": "NoemieP",
        "conceptSlug": "clair-obscur",
        "images": []
    },
    {
        "user": "NoemieP",
        "conceptSlug": "icones-pop",
        "images": []
    },
    {
        "user": "NoemieP",
        "conceptSlug": "terres-sauvages",
        "images": []
    },
    {
        "user": "RachelP",
        "conceptSlug": "art-abstrait",
        "images": []
    },
    {
        "user": "RachelP",
        "conceptSlug": "mise-en-scene-des-medias",
        "images": []
    },
    {
        "user": "RachelP",
        "conceptSlug": "publicites-conceptuelles",
        "images": []
    },
    {
        "user": "RachelP",
        "conceptSlug": "schemas-explicatifs",
        "images": []
    },
    {
        "user": "RatonG",
        "conceptSlug": "cinemagraph",
        "images": []
    },
    {
        "user": "RatonG",
        "conceptSlug": "distorsions-refractions",
        "images": []
    },
    {
        "user": "RatonG",
        "conceptSlug": "festivals-du-monde",
        "images": []
    },
    {
        "user": "RatonG",
        "conceptSlug": "ui-ux-design",
        "images": []
    },
    {
        "user": "SantiagoB",
        "conceptSlug": "abstraction-coloree",
        "images": [
            {
                "path": "SantiagoB/abstraction-coloree/Automne.ori.jpg",
                "width": 4608,
                "height": 2592,
                "ratio": 1.7777777777777777
            },
            {
                "path": "SantiagoB/abstraction-coloree/Bugs.ori.jpg",
                "width": 5184,
                "height": 3456,
                "ratio": 1.5
            },
            {
                "path": "SantiagoB/abstraction-coloree/Cotton_Candy.ori.jpg",
                "width": 4916,
                "height": 3360,
                "ratio": 1.463095238095238
            },
            {
                "path": "SantiagoB/abstraction-coloree/Flags.ori.jpg",
                "width": 5184,
                "height": 3456,
                "ratio": 1.5
            },
            {
                "path": "SantiagoB/abstraction-coloree/Graffity.ori.jpg",
                "width": 2048,
                "height": 1366,
                "ratio": 1.499267935578331
            },
            {
                "path": "SantiagoB/abstraction-coloree/Hammaks.ori.jpg",
                "width": 5184,
                "height": 3456,
                "ratio": 1.5
            },
            {
                "path": "SantiagoB/abstraction-coloree/Legos.ori.jpg",
                "width": 6000,
                "height": 4000,
                "ratio": 1.5
            },
            {
                "path": "SantiagoB/abstraction-coloree/Long_Exposure.ori.jpg",
                "width": 2048,
                "height": 1366,
                "ratio": 1.499267935578331
            },
            {
                "path": "SantiagoB/abstraction-coloree/Out_of_Focus.ori.jpg",
                "width": 5184,
                "height": 3456,
                "ratio": 1.5
            },
            {
                "path": "SantiagoB/abstraction-coloree/Rain.ori.jpg",
                "width": 5184,
                "height": 3456,
                "ratio": 1.5
            }
        ]
    },
    {
        "user": "SantiagoB",
        "conceptSlug": "histoires-humaines",
        "images": [
            {
                "path": "SantiagoB/histoires-humaines/BreackDance.ori.jpg",
                "width": 4830,
                "height": 3170,
                "ratio": 1.523659305993691
            },
            {
                "path": "SantiagoB/histoires-humaines/Chasse_Balcon.ori.jpg",
                "width": 5184,
                "height": 3456,
                "ratio": 1.5
            },
            {
                "path": "SantiagoB/histoires-humaines/Chilling.ori.jpg",
                "width": 5184,
                "height": 3456,
                "ratio": 1.5
            },
            {
                "path": "SantiagoB/histoires-humaines/Danser.ori.jpg",
                "width": 4764,
                "height": 3227,
                "ratio": 1.4762937713046174
            },
            {
                "path": "SantiagoB/histoires-humaines/Fermeture_de_caisse.ori.jpg",
                "width": 5028,
                "height": 3352,
                "ratio": 1.5
            },
            {
                "path": "SantiagoB/histoires-humaines/Mariage_1.ori.jpg",
                "width": 5795,
                "height": 3260,
                "ratio": 1.7776073619631902
            },
            {
                "path": "SantiagoB/histoires-humaines/Mariage_2.ori.jpg",
                "width": 3848,
                "height": 5564,
                "ratio": 0.6915887850467289
            },
            {
                "path": "SantiagoB/histoires-humaines/Spectacle_Urbain.ori.jpg",
                "width": 5184,
                "height": 3456,
                "ratio": 1.5
            },
            {
                "path": "SantiagoB/histoires-humaines/Vacances.ori.jpg",
                "width": 4473,
                "height": 3008,
                "ratio": 1.487034574468085
            },
            {
                "path": "SantiagoB/histoires-humaines/Vente_de_limonade.ori.jpg",
                "width": 4671,
                "height": 3271,
                "ratio": 1.4280036686028736
            }
        ]
    },
    {
        "user": "SantiagoB",
        "conceptSlug": "portrait-de-rue",
        "images": [
            {
                "path": "SantiagoB/portrait-de-rue/Bonaventure.ori.jpg",
                "width": 5028,
                "height": 3352,
                "ratio": 1.5
            },
            {
                "path": "SantiagoB/portrait-de-rue/Dancing_Queen.ori.jpg",
                "width": 3373,
                "height": 5059,
                "ratio": 0.6667325558410753
            },
            {
                "path": "SantiagoB/portrait-de-rue/Fin_de_shift.ori.jpg",
                "width": 5184,
                "height": 3456,
                "ratio": 1.5
            },
            {
                "path": "SantiagoB/portrait-de-rue/Happy_Musician.ori.jpg",
                "width": 3456,
                "height": 5184,
                "ratio": 0.6666666666666666
            },
            {
                "path": "SantiagoB/portrait-de-rue/Manifestation.ori.jpg",
                "width": 4000,
                "height": 6000,
                "ratio": 0.6666666666666666
            },
            {
                "path": "SantiagoB/portrait-de-rue/New_Menu.ori.jpg",
                "width": 5184,
                "height": 3456,
                "ratio": 1.5
            },
            {
                "path": "SantiagoB/portrait-de-rue/On_the_ground.ori.jpg",
                "width": 5184,
                "height": 3456,
                "ratio": 1.5
            },
            {
                "path": "SantiagoB/portrait-de-rue/SummerTime.ori.jpg",
                "width": 4741,
                "height": 3161,
                "ratio": 1.499841822208162
            },
            {
                "path": "SantiagoB/portrait-de-rue/TamTams.ori.jpg",
                "width": 2048,
                "height": 1366,
                "ratio": 1.499267935578331
            },
            {
                "path": "SantiagoB/portrait-de-rue/Waiting_the_bus.ori.jpg",
                "width": 4359,
                "height": 2912,
                "ratio": 1.4969093406593406
            }
        ]
    },
    {
        "user": "SantiagoB",
        "conceptSlug": "realite-augmentee",
        "images": []
    },
    {
        "user": "SarahL",
        "conceptSlug": "photojournalisme-de-guerre",
        "images": []
    },
    {
        "user": "SarahL",
        "conceptSlug": "post-apocalypse",
        "images": []
    },
    {
        "user": "SarahL",
        "conceptSlug": "sursaturation",
        "images": []
    },
    {
        "user": "SarahL",
        "conceptSlug": "tilt-shift",
        "images": []
    },
    {
        "user": "SashaB",
        "conceptSlug": "double-exposition",
        "images": []
    },
    {
        "user": "SashaB",
        "conceptSlug": "guides-de-conception",
        "images": []
    },
    {
        "user": "SashaB",
        "conceptSlug": "paysages-oniriques",
        "images": []
    },
    {
        "user": "SashaB",
        "conceptSlug": "rites-et-rituels",
        "images": []
    },
    {
        "user": "ThierryS",
        "conceptSlug": "chronophotographie",
        "images": []
    },
    {
        "user": "ThierryS",
        "conceptSlug": "comparatifs-avant-apres",
        "images": []
    },
    {
        "user": "ThierryS",
        "conceptSlug": "infographies-publicitaire",
        "images": []
    },
    {
        "user": "ThierryS",
        "conceptSlug": "nature-morte",
        "images": []
    },
    {
        "user": "ThomasXavierM",
        "conceptSlug": "desintegration-numerique",
        "images": []
    },
    {
        "user": "ThomasXavierM",
        "conceptSlug": "portraits-ethniques",
        "images": []
    },
    {
        "user": "ThomasXavierM",
        "conceptSlug": "publicites-vintage",
        "images": []
    },
    {
        "user": "ThomasXavierM",
        "conceptSlug": "time-lapse",
        "images": []
    },
    {
        "user": "TomH",
        "conceptSlug": "faune-en-action",
        "images": []
    },
    {
        "user": "TomH",
        "conceptSlug": "infrarouge",
        "images": []
    },
    {
        "user": "TomH",
        "conceptSlug": "macro-monde-microscopique",
        "images": []
    },
    {
        "user": "TomH",
        "conceptSlug": "portraits-sociaux",
        "images": []
    },
    {
        "user": "UgoJ",
        "conceptSlug": "carnet-de-voyage",
        "images": []
    },
    {
        "user": "UgoJ",
        "conceptSlug": "mises-en-abyme",
        "images": []
    },
    {
        "user": "UgoJ",
        "conceptSlug": "objets-du-quotidien",
        "images": []
    },
    {
        "user": "UgoJ",
        "conceptSlug": "portraits-emotionnels",
        "images": []
    }
]